pretalx_rocket/__init__.py
pretalx_rocket/apps.py
pretalx_rocket/forms.py
pretalx_rocket/models.py
pretalx_rocket/signals.py
pretalx_rocket/urls.py
pretalx_rocket/views.py
pretalx_rocket/migrations/0001_initial.py
pretalx_rocket/migrations/__init__.py
pretalx_rocket/static/pretalx_rocket/.gitkeep
pretalx_rocket/templates/pretalx_rocket/settings.html
pretalx_rocket-2024.4.0.dist-info/LICENSE
pretalx_rocket-2024.4.0.dist-info/METADATA
pretalx_rocket-2024.4.0.dist-info/WHEEL
pretalx_rocket-2024.4.0.dist-info/entry_points.txt
pretalx_rocket-2024.4.0.dist-info/top_level.txt
pretalx_rocket-2024.4.0.dist-info/RECORD
