Metadata-Version: 2.1
Name: pretalx-rocket
Version: 2024.4.0
Summary: pretalx plugin to send notifications about changes to submissions to a Rocket.Chat channel
Author-email: Florian Moesch <florian@moesch.org>
Maintainer-email: Florian Moesch <florian@moesch.org>
License: Apache Software License
Project-URL: homepage, https://github.com/badbadc0ffee/pretalx-rocket
Project-URL: repository, https://github.com/badbadc0ffee/pretalx-rocket.git
Keywords: pretalx
License-File: LICENSE
Requires-Dist: rocketchat-API
Provides-Extra: dev
Requires-Dist: black; extra == "dev"
Requires-Dist: build; extra == "dev"
Requires-Dist: check-manifest; extra == "dev"
Requires-Dist: flake8; extra == "dev"
Requires-Dist: isort; extra == "dev"
